LICENSE
MANIFEST.in
README.md
setup.cfg
setup.py
fultrader/__init__.py
fultrader.egg-info/PKG-INFO
fultrader.egg-info/SOURCES.txt
fultrader.egg-info/dependency_links.txt
fultrader.egg-info/not-zip-safe
fultrader.egg-info/requires.txt
fultrader.egg-info/top_level.txt
fultrader/data/__init__.py
fultrader/data/add.py
fultrader/database/__init__.py
fultrader/database/test.py
fultrader/factor/__init__.py
fultrader/factor/factor.py