Metadata-Version: 2.1
Name: fultrader
Version: 0.1.1.1
Summary: A framework for developing quant to trade
Home-page: UNKNOWN
Author: DanBin Dai
Author-email: 674416630@qq.com
License: MIT
Keywords: quant,quantitative,investment,trading,fulture trader,trading,commodity
Platform: UNKNOWN
Classifier: Operating System :: Microsoft :: Windows
Classifier: Operating System :: POSIX :: Linux
Classifier: Operating System :: MacOS
Classifier: Programming Language :: Python :: 3.9
Classifier: Programming Language :: Python :: 3.10
Classifier: Topic :: Office/Business :: Financial :: Investment
Classifier: Programming Language :: Python :: Implementation :: CPython
Classifier: License :: OSI Approved :: MIT License
Classifier: Natural Language :: Chinese (Simplified)
Requires-Python: >=3.9
License-File: LICENSE
